openhems/__init__.py
openhems/check_homeassistant_api.py
openhems/main.py
openhems/server.py
openhems/server_vpn.py
openhems/data/keys_en.yaml
openhems/data/keys_fr.yaml
openhems/data/openhems_default.yaml
openhems/data/openhems_default_docker.yaml
openhems/data/openhems_tooltips_en.yaml
openhems/data/openhems_tooltips_fr.yaml
openhems/emhass/gunicorn.conf.py
openhems/emhass/options.json
openhems/emhass/data/data_load_cost_forecast.csv
openhems/emhass/data/data_load_forecast.csv
openhems/emhass/data/data_prod_price_forecast.csv
openhems/emhass/data/data_weather_forecast.csv
openhems/emhass/data/heating_prediction.csv
openhems/emhass/data/long_train_data.pkl
openhems/emhass/data/opt_res_latest.csv
openhems/emhass/data/opt_res_perfect_optim_cost.csv
openhems/emhass/data/opt_res_perfect_optim_profit.csv
openhems/emhass/data/opt_res_perfect_optim_self-consumption.csv
openhems/emhass/data/test_df_final.pkl
openhems/emhass/data/test_response_get_data_get_method.pbz2
openhems/emhass/data/test_response_openmeteo_get_method.pbz2
openhems/emhass/data/test_response_scrapper_get_method.pbz2
openhems/emhass/data/test_response_solarforecast_get_method.pbz2
openhems/emhass/data/test_response_solcast_get_method.pbz2
openhems/emhass/docs/conf.py
openhems/emhass/scripts/load_clustering.py
openhems/emhass/scripts/load_forecast_sklearn.py
openhems/emhass/scripts/optim_results_analysis.py
openhems/emhass/scripts/read_csv_plot_data.py
openhems/emhass/scripts/save_pvlib_module_inverter_database.py
openhems/emhass/scripts/script_debug_forecasts.py
openhems/emhass/scripts/script_debug_optim.py
openhems/emhass/scripts/script_simple_thermal_model.py
openhems/emhass/scripts/script_thermal_model_optim.py
openhems/emhass/scripts/special_config_analysis.py
openhems/emhass/scripts/special_options.json
openhems/emhass/scripts/use_cases_analysis.py
openhems/emhass/src/emhass/__init__.py
openhems/emhass/src/emhass/command_line.py
openhems/emhass/src/emhass/forecast.py
openhems-0.2.15.dist-info/licenses/LICENSE
openhems-0.2.15.dist-info/METADATA
openhems-0.2.15.dist-info/WHEEL
openhems-0.2.15.dist-info/top_level.txt
openhems-0.2.15.dist-info/RECORD
