Metadata-Version: 2.4
Name: openhems
Version: 0.2.15
Summary: A sample Home Energy Managment System based on Home-Assistant
Home-page: https://github.com/abriotde/openhems-sample.git
Author: OpenHomeSystem
Author-email: OpenHomeSystem <contact@openhomesystem.com>
Maintainer-email: Albéric de la Crochais <alberic.delacrochais@protonmail.com>
License:                     GNU GENERAL PUBLIC LICENSE
Project-URL: Homepage, https://openhomesystem.com
Project-URL: Issues, https://github.com/abriotde/openhems-sample/issues
Project-URL: Documentation, https://openhems.readthedocs.io/en/latest/
Project-URL: Repository, https://github.com/abriotde/openhems-sample.git
Keywords: energy,HEMS,home automation,home-assistant,domotic
Classifier: Development Status :: 5 - Production/Stable
Classifier: Intended Audience :: End Users/Desktop
Classifier: Topic :: Software Development :: Build Tools
Classifier: Operating System :: POSIX :: Linux
Classifier: Programming Language :: Python :: 3 :: Only
Classifier: Framework :: Pyramid
Classifier: Topic :: Home Automation
Classifier: Natural Language :: English
Classifier: Natural Language :: French
Requires-Python: >=3.8, <4
License-File: LICENSE
Requires-Dist: requests
Requires-Dist: pandas
Requires-Dist: pyyaml
Requires-Dist: pyramid
Requires-Dist: pyramid-jinja2
Requires-Dist: packaging
Requires-Dist: astral
Requires-Dist: GitPython
Requires-Dist: toml
Requires-Dist: scikit-opt
Requires-Dist: scikit-opt
Requires-Dist: numpy
Requires-Dist: plotly
Requires-Dist: scikit-learn
Requires-Dist: skforecast
Requires-Dist: pvlib
Requires-Dist: beautifulsoup4
Requires-Dist: protobuf
Requires-Dist: pandas
Requires-Dist: scipy
Requires-Dist: h5py
Requires-Dist: pulp
Dynamic: author
Dynamic: home-page
Dynamic: license-file
Dynamic: requires-python
